wikipedia2vec/__init__.py
wikipedia2vec/cli.py
wikipedia2vec/dictionary.cp310-win_amd64.pyd
wikipedia2vec/dictionary.cpp
wikipedia2vec/dictionary.pxd
wikipedia2vec/dictionary.py
wikipedia2vec/dump_db.cp310-win_amd64.pyd
wikipedia2vec/dump_db.cpp
wikipedia2vec/dump_db.pxd
wikipedia2vec/dump_db.py
wikipedia2vec/link_graph.cp310-win_amd64.pyd
wikipedia2vec/link_graph.cpp
wikipedia2vec/link_graph.py
wikipedia2vec/mention_db.cp310-win_amd64.pyd
wikipedia2vec/mention_db.cpp
wikipedia2vec/mention_db.pxd
wikipedia2vec/mention_db.py
wikipedia2vec/wikipedia2vec.cp310-win_amd64.pyd
wikipedia2vec/wikipedia2vec.cpp
wikipedia2vec/wikipedia2vec.py
wikipedia2vec/utils/__init__.py
wikipedia2vec/utils/utils.py
wikipedia2vec/utils/wiki_dump_reader.py
wikipedia2vec/utils/wiki_page.cp310-win_amd64.pyd
wikipedia2vec/utils/wiki_page.cpp
wikipedia2vec/utils/wiki_page.pxd
wikipedia2vec/utils/wiki_page.py
wikipedia2vec/utils/sentence_detector/__init__.py
wikipedia2vec/utils/sentence_detector/base_sentence_detector.py
wikipedia2vec/utils/sentence_detector/icu_sentence_detector.py
wikipedia2vec/utils/sentence_detector/sentence.cp310-win_amd64.pyd
wikipedia2vec/utils/sentence_detector/sentence.cpp
wikipedia2vec/utils/sentence_detector/sentence.pxd
wikipedia2vec/utils/sentence_detector/sentence.py
wikipedia2vec/utils/tokenizer/__init__.py
wikipedia2vec/utils/tokenizer/base_tokenizer.py
wikipedia2vec/utils/tokenizer/icu_tokenizer.py
wikipedia2vec/utils/tokenizer/jieba_tokenizer.py
wikipedia2vec/utils/tokenizer/mecab_tokenizer.py
wikipedia2vec/utils/tokenizer/regexp_tokenizer.py
wikipedia2vec/utils/tokenizer/token.cp310-win_amd64.pyd
wikipedia2vec/utils/tokenizer/token.cpp
wikipedia2vec/utils/tokenizer/token.pxd
wikipedia2vec/utils/tokenizer/token.py
wikipedia2vec-2.0.0.dist-info/LICENSE
wikipedia2vec-2.0.0.dist-info/METADATA
wikipedia2vec-2.0.0.dist-info/WHEEL
wikipedia2vec-2.0.0.dist-info/entry_points.txt
wikipedia2vec-2.0.0.dist-info/top_level.txt
wikipedia2vec-2.0.0.dist-info/RECORD
