Metadata-Version: 2.1
Name: wikipedia2vec
Version: 2.0.0
Summary: A tool for learning vector representations of words and entities from Wikipedia
Home-page: http://wikipedia2vec.github.io/
Author: Studio Ousia
Author-email: ikuya@ousia.jp
Keywords: wikipedia,embedding,wikipedia2vec
Classifier: Development Status :: 5 - Production/Stable
Classifier: Intended Audience :: Developers
Classifier: Natural Language :: English
Classifier: License :: OSI Approved :: Apache Software License
Classifier: Programming Language :: Python
Classifier: Programming Language :: Python :: 3.8
Classifier: Programming Language :: Python :: 3.9
Classifier: Programming Language :: Python :: 3.10
Classifier: Programming Language :: Python :: 3.11
Classifier: Programming Language :: Python :: 3.12
Requires-Python: >=3.8
License-File: LICENSE
Requires-Dist: click
Requires-Dist: jieba
Requires-Dist: joblib
Requires-Dist: lmdb
Requires-Dist: marisa-trie
Requires-Dist: mwparserfromhell
Requires-Dist: numpy
Requires-Dist: scipy
Requires-Dist: tqdm
Provides-Extra: icu
Requires-Dist: PyICU ; extra == 'icu'
Provides-Extra: mecab
Requires-Dist: mecab-python3 ; extra == 'mecab'
Requires-Dist: unidic-lite ; extra == 'mecab'
